dbsys/__init__.py
dbsys/dbsys.py
dbsys/dbsys.pyi
dbsys/py.typed
dbsys-0.7.9.dist-info/LICENSE
dbsys-0.7.9.dist-info/METADATA
dbsys-0.7.9.dist-info/WHEEL
dbsys-0.7.9.dist-info/top_level.txt
dbsys-0.7.9.dist-info/RECORD
