Metadata-Version: 2.1
Name: dbsys
Version: 0.7.9
Summary: A comprehensive library for managing database operations using SQLAlchemy, pandas, and Redis
Home-page: https://github.com/lifsys/dbsys
Author: Mark Powers
Author-email: mpoweru@lifsys.com
Project-URL: Bug Tracker, https://github.com/lifsys/dbsys/issues
Project-URL: Documentation, https://github.com/lifsys/dbsys/blob/main/README.md
Project-URL: Source Code, https://github.com/lifsys/dbsys
Keywords: database sqlalchemy pandas redis orm data management
Classifier: Development Status :: 4 - Beta
Classifier: Intended Audience :: Developers
Classifier: License :: OSI Approved :: MIT License
Classifier: Operating System :: OS Independent
Classifier: Programming Language :: Python :: 3
Classifier: Programming Language :: Python :: 3.8
Classifier: Programming Language :: Python :: 3.9
Classifier: Programming Language :: Python :: 3.10
Classifier: Programming Language :: Python :: 3.11
Classifier: Programming Language :: Python :: 3.12
Classifier: Topic :: Database
Classifier: Topic :: Software Development :: Libraries :: Python Modules
Classifier: Typing :: Typed
Requires-Python: >=3.8
License-File: LICENSE
Requires-Dist: pandas<3.0.0,>=1.0.0
Requires-Dist: sqlalchemy<3.0.0,>=1.4.0
Requires-Dist: redis<5.0.0,>=3.5.0
Provides-Extra: dev
Requires-Dist: pytest>=7.0; extra == "dev"
Requires-Dist: pytest-cov>=3.0; extra == "dev"
Requires-Dist: flake8>=4.0; extra == "dev"
Requires-Dist: black>=22.0; extra == "dev"
Requires-Dist: mypy>=0.900; extra == "dev"
Requires-Dist: isort>=5.0; extra == "dev"
